{
	"schemaVersion": 1,
	"id": "inventory",
	"version": "${version}",
	"name": "Frostbyte's Improved Inventory",
	"description": "Makes parts of the inventory and HUD more useful",
	"authors": [
		"FrostbyteGames"
	],
	"contact": {

	},
	"license": "CC-BY-NC",
	"icon": "assets/inventory/icon.png",
	"environment": "*",
	"entrypoints": {
		"main": [
			"net.frostbyte.inventory.ImprovedInventory"
		],
		"modmenu": [
			"net.frostbyte.inventory.config.ModMenuIntegration"
		]
	},
	"mixins": [
		"inventory.mixins.json"
	],
	"accessWidener": "inventory.accesswidener",
	"depends": {
		"fabricloader": ">=0.16.13",
		"minecraft": "1.21.6",
		"java": ">=21",
		"fabric-api": "*",
		"yet_another_config_lib_v3": ">=3.7.1+1.21.6-fabric"
	},
	"suggests": {
		"modmenu": ">=15.0.0-beta.2"
	}
}